<?xml version="1.0" encoding="utf-8"?>
<LanguageData>

  <!-- buffs 1 -->

  <TMS_armor_Sharp1.label>利器防护-初级</TMS_armor_Sharp1.label>
  <TMS_armor_Sharp2.label>利器防护-中级</TMS_armor_Sharp2.label>
  <TMS_armor_Sharp3.label>利器防护-高级</TMS_armor_Sharp3.label>
  <TMS_armor_Sharp4.label>利器防护-特级</TMS_armor_Sharp4.label>
  <TMS_armor_Sharp5.label>利器防护-终极</TMS_armor_Sharp5.label>
  <TMS_armor_Blunt1.label>钝器防护-初级</TMS_armor_Blunt1.label>
  <TMS_armor_Blunt2.label>钝器防护-中级</TMS_armor_Blunt2.label>
  <TMS_armor_Blunt3.label>钝器防护-高级</TMS_armor_Blunt3.label>
  <TMS_armor_Blunt4.label>钝器防护-特级</TMS_armor_Blunt4.label>
  <TMS_armor_Blunt5.label>钝器防护-终极</TMS_armor_Blunt5.label>
  <TMS_armor_Heat1.label>热能防护-初级</TMS_armor_Heat1.label>
  <TMS_armor_Heat2.label>热能防护-中级</TMS_armor_Heat2.label>
  <TMS_armor_Heat3.label>热能防护-高级</TMS_armor_Heat3.label>
  <TMS_armor_Heat4.label>热能防护-特级</TMS_armor_Heat4.label>
  <TMS_armor_Heat5.label>热能防护-终极</TMS_armor_Heat5.label>
  <TMS_HungerRate1.label>辟谷-初级</TMS_HungerRate1.label>
  <TMS_HungerRate2.label>辟谷-中级</TMS_HungerRate2.label>
  <TMS_HungerRate3.label>辟谷-高级</TMS_HungerRate3.label>
  <TMS_HungerRate4.label>辟谷-特级</TMS_HungerRate4.label>
  <TMS_HungerRate5.label>辟谷-终极</TMS_HungerRate5.label>
  <TMS_MeleeDodgeChance1.label>敏捷-初级</TMS_MeleeDodgeChance1.label>
  <TMS_MeleeDodgeChance2.label>敏捷-中级</TMS_MeleeDodgeChance2.label>
  <TMS_MeleeDodgeChance3.label>敏捷-高级</TMS_MeleeDodgeChance3.label>
  <TMS_MeleeDodgeChance4.label>敏捷-特级</TMS_MeleeDodgeChance4.label>
  <TMS_MeleeDodgeChance5.label>敏捷-终极</TMS_MeleeDodgeChance5.label>
  <TMS_MoveSpeed1.label>轻灵-初级</TMS_MoveSpeed1.label>
  <TMS_MoveSpeed2.label>轻灵-中级</TMS_MoveSpeed2.label>
  <TMS_MoveSpeed3.label>轻灵-高级</TMS_MoveSpeed3.label>
  <TMS_MoveSpeed4.label>轻灵-特级</TMS_MoveSpeed4.label>
  <TMS_MoveSpeed5.label>轻灵-终级</TMS_MoveSpeed5.label>
  <TMS_ComfyTemperature1.label>适应力-初级</TMS_ComfyTemperature1.label>
  <TMS_ComfyTemperature2.label>适应力-中级</TMS_ComfyTemperature2.label>
  <TMS_ComfyTemperature3.label>适应力-高级</TMS_ComfyTemperature3.label>
  <TMS_ComfyTemperature4.label>适应力-特级</TMS_ComfyTemperature4.label>
  <TMS_ComfyTemperature5.label>适应力-终级</TMS_ComfyTemperature5.label>
  <TMS_BloodFiltration1.label>除秽-初级</TMS_BloodFiltration1.label>
  <TMS_BloodFiltration2.label>除秽-中级</TMS_BloodFiltration2.label>
  <TMS_BloodFiltration3.label>除秽-高级</TMS_BloodFiltration3.label>
  <TMS_BloodFiltration4.label>除秽-特级</TMS_BloodFiltration4.label>
  <TMS_BloodFiltration5.label>除秽-终级</TMS_BloodFiltration5.label>
  <TMS_MeleeHitChance1.label>鹰眼-初级</TMS_MeleeHitChance1.label>
  <TMS_MeleeHitChance2.label>鹰眼-中级</TMS_MeleeHitChance2.label>
  <TMS_MeleeHitChance3.label>鹰眼-高级</TMS_MeleeHitChance3.label>
  <TMS_MeleeHitChance4.label>鹰眼-特级</TMS_MeleeHitChance4.label>
  <TMS_MeleeHitChance5.label>鹰眼-终级</TMS_MeleeHitChance5.label>
  <TMS_Manipulation1.label>妙手-初级</TMS_Manipulation1.label>
  <TMS_Manipulation2.label>妙手-中级</TMS_Manipulation2.label>
  <TMS_Manipulation3.label>妙手-高级</TMS_Manipulation3.label>
  <TMS_Manipulation4.label>妙手-特级</TMS_Manipulation4.label>
  <TMS_Manipulation5.label>妙手-终级</TMS_Manipulation5.label>
  <TMS_Breathing1.label>吐纳-初级</TMS_Breathing1.label>
  <TMS_Breathing2.label>吐纳-中级</TMS_Breathing2.label>
  <TMS_Breathing3.label>吐纳-高级</TMS_Breathing3.label>
  <TMS_Breathing4.label>吐纳-特级</TMS_Breathing4.label>
  <TMS_Breathing5.label>吐纳-终级</TMS_Breathing5.label>


</LanguageData>